LICENSE.txt
MANIFEST.in
README.rst
setup.py
examples/mptrain.py
examples/ocr.py
examples/sin.py
examples/stock.py
examples/xor.py
examples/data/black-scholes.dat
examples/data/ocr.dat
ffnet/__init__.py
ffnet/_mpprop.py
ffnet/_py2f.py
ffnet/_tests.py
ffnet/_version.py
ffnet/compat.py
ffnet/ffnet.py
ffnet/graphs.py
ffnet/pikaia.py
ffnet.egg-info/PKG-INFO
ffnet.egg-info/SOURCES.txt
ffnet.egg-info/dependency_links.txt
ffnet.egg-info/requires.txt
ffnet.egg-info/top_level.txt
ffnet/fortran/__init__.py
ffnet/fortran/compile.py
ffnet/fortran/ffnet.f
ffnet/fortran/pikaia.f